prolint/__init__.py
prolint/analysis/__init__.py
prolint/analysis/base.py
prolint/analysis/density.py
prolint/analysis/distances.py
prolint/analysis/kinetics.py
prolint/analysis/metrics.py
prolint/analysis/shared_contacts.py
prolint/analysis/timeseries.py
prolint/computers/__init__.py
prolint/computers/base.py
prolint/computers/contacts.py
prolint/config/__init__.py
prolint/config/colors.py
prolint/config/enums.py
prolint/config/logging.py
prolint/config/theme.json
prolint/config/units.py
prolint/contacts/__init__.py
prolint/contacts/base.py
prolint/contacts/exact_contacts.py
prolint/core/__init__.py
prolint/core/contact_provider.py
prolint/core/groups.py
prolint/core/replica_detection.py
prolint/core/universe.py
prolint/plotting/__init__.py
prolint/plotting/base.py
prolint/plotting/density.py
prolint/plotting/heatmap.py
prolint/plotting/kinetics.py
prolint/plotting/network.py
prolint/plotting/residues.py
prolint/plotting/structure.py
prolint/plotting/theme.py
prolint/plotting/timeseries.py
prolint/utils/__init__.py
prolint/utils/utils.py
prolint/web/README.md
prolint/web/__init__.py
prolint/web/requirements.txt
prolint/web/backend/__init__.py
prolint/web/backend/main.py
prolint/web/backend/api/__init__.py
prolint/web/backend/api/dashboard.py
prolint/web/backend/api/datasets.py
prolint/web/backend/models/__init__.py
prolint/web/backend/models/schemas.py
prolint/web/backend/services/__init__.py
prolint/web/backend/services/dataset_service.py
prolint/web/backend/services/interaction_service.py
prolint/web/backend/services/storage_service.py
prolint/web/backend/websocket/__init__.py
prolint/web/backend/websocket/manager.py
prolint/web/frontend/index.html
prolint/web/frontend/nginx.conf
prolint/web/frontend/package-lock.json
prolint/web/frontend/package.json
prolint/web/frontend/tsconfig.json
prolint/web/frontend/tsconfig.node.json
prolint/web/frontend/vite.config.ts
prolint/web/frontend/node_modules/flatted/python/flatted.py
prolint/web/frontend/src/App.tsx
prolint-2.0.0.dist-info/METADATA
prolint-2.0.0.dist-info/WHEEL
prolint-2.0.0.dist-info/top_level.txt
prolint-2.0.0.dist-info/RECORD
