Metadata-Version: 2.4
Name: prolint
Version: 2.0.0
Summary: Biomolecular Interaction Analysis from Molecular Dynamics Simulations
Author: Daniel P. Ramirez-Echemendia, Besian I. Sejdiu
License: MIT
Project-URL: Homepage, https://github.com/ProLint/prolint
Project-URL: Documentation, https://prolint.github.io/prolint
Project-URL: Repository, https://github.com/ProLint/prolint
Project-URL: Issues, https://github.com/ProLint/prolint/issues
Keywords: molecular-dynamics,biomolecular-interactions,contact-analysis,biophysics,MDAnalysis
Classifier: Development Status :: 4 - Beta
Classifier: Intended Audience :: Science/Research
Classifier: License :: OSI Approved :: MIT License
Classifier: Operating System :: OS Independent
Classifier: Programming Language :: Python :: 3
Classifier: Programming Language :: Python :: 3.9
Classifier: Programming Language :: Python :: 3.10
Classifier: Programming Language :: Python :: 3.11
Classifier: Programming Language :: Python :: 3.12
Classifier: Topic :: Scientific/Engineering :: Bio-Informatics
Classifier: Topic :: Scientific/Engineering :: Chemistry
Requires-Python: >=3.9
Requires-Dist: MDAnalysis>=2.4.0
Requires-Dist: numpy>=1.21.0
Requires-Dist: matplotlib>=3.5.0
Requires-Dist: networkx>=2.8.0
Requires-Dist: scipy>=1.9.0
Provides-Extra: web
Requires-Dist: fastapi>=0.109.0; extra == "web"
Requires-Dist: uvicorn[standard]>=0.27.0; extra == "web"
Requires-Dist: python-multipart>=0.0.6; extra == "web"
Requires-Dist: websockets>=12.0; extra == "web"
Provides-Extra: docs
Requires-Dist: sphinx>=7.0.0; extra == "docs"
Requires-Dist: furo>=2024.1.0; extra == "docs"
Requires-Dist: myst-parser>=3.0.0; extra == "docs"
Requires-Dist: sphinx-copybutton>=0.5.0; extra == "docs"
Requires-Dist: sphinx-design>=0.5.0; extra == "docs"
Requires-Dist: sphinx-autoapi>=3.0.0; extra == "docs"
Provides-Extra: dev
Requires-Dist: pytest>=7.0.0; extra == "dev"
Requires-Dist: pytest-cov>=4.0.0; extra == "dev"
Requires-Dist: pytest-mock>=3.12.0; extra == "dev"
Requires-Dist: black>=23.0.0; extra == "dev"
Requires-Dist: ruff>=0.1.0; extra == "dev"
Provides-Extra: all
Requires-Dist: prolint[dev,docs,web]; extra == "all"
